LICENSE
fastapi_cloud_logging/__init__.py
fastapi_cloud_logging/fastapi_cloud_logging_handler.py
fastapi_cloud_logging/request_logging_middleware.py
fastapi_cloud_logging/utils.py
fastapi_cloud_logging-1.1.0.dist-info/METADATA
fastapi_cloud_logging-1.1.0.dist-info/LICENSE
fastapi_cloud_logging-1.1.0.dist-info/WHEEL
fastapi_cloud_logging-1.1.0.dist-info/RECORD
