Metadata-Version: 2.1
Name: fastapi-cloud-logging
Version: 1.1.0
Summary: Cloud Logging For FastAPI
Home-page: https://github.com/quoth/fastapi-cloud-logging
License: MIT
Author: quoth
Author-email: 4wordextinguisher@gmail.com
Requires-Python: >=3.7,<4.0
Classifier: Environment :: Web Environment
Classifier: Framework :: FastAPI
Classifier: License :: OSI Approved :: MIT License
Classifier: Programming Language :: Python :: 3
Classifier: Programming Language :: Python :: 3.7
Classifier: Programming Language :: Python :: 3.8
Classifier: Programming Language :: Python :: 3.9
Classifier: Programming Language :: Python :: 3.10
Classifier: Programming Language :: Python :: 3.11
Classifier: Topic :: Software Development :: Libraries :: Python Modules
Classifier: Topic :: System :: Logging
Provides-Extra: local
Provides-Extra: py37
Requires-Dist: fastapi (>=0.71)
Requires-Dist: google-cloud-logging (>=3,<4)
Project-URL: Repository, https://github.com/quoth/fastapi-cloud-logging
